gdal.py
gdalconst.py
ogr.py
osr.py
osgeo/__init__.py
osgeo/_gdal.cpython-37m-x86_64-linux-gnu.so
osgeo/_gdalconst.cpython-37m-x86_64-linux-gnu.so
osgeo/_ogr.cpython-37m-x86_64-linux-gnu.so
osgeo/_osr.cpython-37m-x86_64-linux-gnu.so
osgeo/gdal.py
osgeo/gdal_array.py
osgeo/gdalconst.py
osgeo/gdalnumeric.py
osgeo/gnm.py
osgeo/ogr.py
osgeo/osr.py
osgeo/.libs/libcom_err-beb60336.so.2.1
osgeo/.libs/libcrypto-de69073a.so.0.9.8e
osgeo/.libs/libcurl-26a7e03e.so.4.5.0
osgeo/.libs/libexpat-72eb0598.so.0.5.0
osgeo/.libs/libgdal-38c38f01.so.20.1.3
osgeo/.libs/libgeos-3-fc05f4c1.5.0.so
osgeo/.libs/libgeos_c-09576097.so.1.9.0
osgeo/.libs/libgssapi_krb5-174f8956.so.2.2
osgeo/.libs/libjasper-fb9de72f.so.1.0.0
osgeo/.libs/libjson-c-ca0558d5.so.2.0.1
osgeo/.libs/libk5crypto-622ef25b.so.3.1
osgeo/.libs/libkeyutils-1-ff31573b.2.so
osgeo/.libs/libkrb5-fb0d2caa.so.3.3
osgeo/.libs/libkrb5support-d7ce89d4.so.0.1
osgeo/.libs/libproj-65d39e31.so.9.0.0
osgeo/.libs/libselinux-cf8f9094.so.1
osgeo/.libs/libsepol-b4f5b513.so.1
osgeo/.libs/libsqlite3-81f1c9bf.so.0.8.6
osgeo/.libs/libssl-a65b360f.so.0.9.8e
osgeo/.libs/libz-a147dcb0.so.1.2.3
test_GDAL-2.3.9.dist-info/METADATA
test_GDAL-2.3.9.dist-info/WHEEL
test_GDAL-2.3.9.dist-info/top_level.txt
test_GDAL-2.3.9.dist-info/RECORD
